pepsyn/__init__.py
pepsyn/_version.py
pepsyn/cli.py
pepsyn/codons.py
pepsyn/dbg.py
pepsyn/error.py
pepsyn/operations.py
pepsyn/util.py
pepsyn-0.4.1.dist-info/LICENSE.txt
pepsyn-0.4.1.dist-info/METADATA
pepsyn-0.4.1.dist-info/WHEEL
pepsyn-0.4.1.dist-info/entry_points.txt
pepsyn-0.4.1.dist-info/top_level.txt
pepsyn-0.4.1.dist-info/RECORD
