Metadata-Version: 2.1
Name: pepsyn
Version: 0.4.1
Summary: Peptide library design
Home-page: https://github.com/lasersonlab/pepsyn
Author: Laserson Lab
License: Apache License, Version 2.0
Platform: UNKNOWN
Classifier: Programming Language :: Python :: 3
Requires-Dist: click
Requires-Dist: tqdm
Requires-Dist: biopython
Requires-Dist: pyyaml
Requires-Dist: pygtrie
